taskbridgeapp/__init__.py
taskbridgeapp/cli/__init__.py
taskbridgeapp/cli/custom.json
taskbridgeapp/cli/tbcli.py
taskbridgeapp/gui/TaskBridge.py
taskbridgeapp/gui/__init__.py
taskbridgeapp/gui/about.ui
taskbridgeapp/gui/assets/AppIcons/Assets.xcassets/AppIcon.appiconset/100.png
taskbridgeapp/gui/assets/AppIcons/Assets.xcassets/AppIcon.appiconset/102.png
taskbridgeapp/gui/assets/AppIcons/Assets.xcassets/AppIcon.appiconset/1024.png
taskbridgeapp/gui/assets/AppIcons/Assets.xcassets/AppIcon.appiconset/114.png
taskbridgeapp/gui/assets/AppIcons/Assets.xcassets/AppIcon.appiconset/120.png
taskbridgeapp/gui/assets/AppIcons/Assets.xcassets/AppIcon.appiconset/128.png
taskbridgeapp/gui/assets/AppIcons/Assets.xcassets/AppIcon.appiconset/144.png
taskbridgeapp/gui/assets/AppIcons/Assets.xcassets/AppIcon.appiconset/152.png
taskbridgeapp/gui/assets/AppIcons/Assets.xcassets/AppIcon.appiconset/16.png
taskbridgeapp/gui/assets/AppIcons/Assets.xcassets/AppIcon.appiconset/167.png
taskbridgeapp/gui/assets/AppIcons/Assets.xcassets/AppIcon.appiconset/172.png
taskbridgeapp/gui/assets/AppIcons/Assets.xcassets/AppIcon.appiconset/180.png
taskbridgeapp/gui/assets/AppIcons/Assets.xcassets/AppIcon.appiconset/196.png
taskbridgeapp/gui/assets/AppIcons/Assets.xcassets/AppIcon.appiconset/20.png
taskbridgeapp/gui/assets/AppIcons/Assets.xcassets/AppIcon.appiconset/216.png
taskbridgeapp/gui/assets/AppIcons/Assets.xcassets/AppIcon.appiconset/256.png
taskbridgeapp/gui/assets/AppIcons/Assets.xcassets/AppIcon.appiconset/29.png
taskbridgeapp/gui/assets/AppIcons/Assets.xcassets/AppIcon.appiconset/32.png
taskbridgeapp/gui/assets/AppIcons/Assets.xcassets/AppIcon.appiconset/40.png
taskbridgeapp/gui/assets/AppIcons/Assets.xcassets/AppIcon.appiconset/48.png
taskbridgeapp/gui/assets/AppIcons/Assets.xcassets/AppIcon.appiconset/50.png
taskbridgeapp/gui/assets/AppIcons/Assets.xcassets/AppIcon.appiconset/512.png
taskbridgeapp/gui/assets/AppIcons/Assets.xcassets/AppIcon.appiconset/55.png
taskbridgeapp-0.1.3b7.dist-info/LICENSE
taskbridgeapp-0.1.3b7.dist-info/METADATA
taskbridgeapp-0.1.3b7.dist-info/WHEEL
taskbridgeapp-0.1.3b7.dist-info/entry_points.txt
taskbridgeapp-0.1.3b7.dist-info/RECORD
