Metadata-Version: 2.1
Name: TaskBridgeApp
Version: 0.1.3b7
Summary: Export your Apple Reminders & Notes to NextCloud, a local folder, or CalDav - and keep them in sync!
Home-page: https://taskbridge.app/
License: GPL-3.0-or-later
Keywords: sync,note sync,reminder sync,cloud notes,cloud reminders
Author: Keith Vassallo
Author-email: keith@vassallo.cloud
Requires-Python: >=3.10,<3.14
Classifier: Development Status :: 4 - Beta
Classifier: Environment :: MacOS X
Classifier: Intended Audience :: End Users/Desktop
Classifier: License :: OSI Approved :: GNU General Public License v3 or later (GPLv3+)
Classifier: Natural Language :: English
Classifier: Operating System :: MacOS
Classifier: Programming Language :: Python
Classifier: Programming Language :: Python :: 3
Classifier: Programming Language :: Python :: 3.10
Classifier: Programming Language :: Python :: 3.11
Classifier: Programming Language :: Python :: 3.12
Classifier: Programming Language :: Python :: Implementation :: CPython
Classifier: Topic :: Utilities
Requires-Dist: PyQt6 (>=6.6.1,<7.0.0)
Requires-Dist: caldav (>=2.0.1,<3.0.0)
Requires-Dist: darkdetect (>=0.8.0,<0.9.0)
Requires-Dist: keyring (>=25.3.0,<26.0.0)
Requires-Dist: markdown2 (>=2.5.3,<3.0.0)
Requires-Dist: markdownify (>=1.1.0,<2.0.0)
Requires-Dist: poetry-core (>=2.1.3,<3.0.0)
Requires-Dist: schedule (>=1.2.1,<2.0.0)
Project-URL: Repository, https://github.com/keithvassallomt/taskbridge
